mylof/__init__.py
mylof/saveLof.py
mylof-0.0.2.dist-info/LICENSE
mylof-0.0.2.dist-info/METADATA
mylof-0.0.2.dist-info/WHEEL
mylof-0.0.2.dist-info/top_level.txt
mylof-0.0.2.dist-info/RECORD
